README
freetype.pyx
setup.py
Freetype.egg-info/PKG-INFO
Freetype.egg-info/SOURCES.txt
Freetype.egg-info/native_libs.txt
Freetype.egg-info/top_level.txt
