Metadata-Version: 1.0
Name: Freetype
Version: Milestone1
Summary: Freetype 2 library bindings
Home-page: http://indic-computing.sourceforge.net/projects/pyfreetype2.html
Author: Joseph Koshy
Author-email: jkoshy@users.sourceforge.net
License: bsd-style
Platform: UNKNOWN
